postmark_models/__init__.py
postmark_models/message.py
postmark_models-0.1.2.dist-info/LICENSE
postmark_models-0.1.2.dist-info/METADATA
postmark_models-0.1.2.dist-info/WHEEL
postmark_models-0.1.2.dist-info/RECORD
